konigcell/__init__.py
konigcell/__version__.py
konigcell/compute2d.py
konigcell/compute3d.py
konigcell/kc2d.c
konigcell/kc2d.cp39-win_amd64.pyd
konigcell/kc2d.pyx
konigcell/kc3d.c
konigcell/kc3d.cp39-win_amd64.pyd
konigcell/kc3d.pyx
konigcell/mode.py
konigcell/pixels.py
konigcell/utils.py
konigcell/voxels.py
konigcell-0.2.1.dist-info/LICENSE
konigcell-0.2.1.dist-info/METADATA
konigcell-0.2.1.dist-info/WHEEL
konigcell-0.2.1.dist-info/top_level.txt
konigcell-0.2.1.dist-info/RECORD
