Metadata-Version: 2.1
Name: konigcell
Version: 0.2.1
Summary: Quantitative, Fast Grid-Based Fields Calculations in 2D and 3D - Residence Time Distributions, Velocity Grids, Eulerian Cell Projections etc.
Home-page: https://github.com/anicusan/KonigCell
Author: Andrei Leonard Nicusan
Author-email: a.l.nicusan@bham.ac.uk
License: MIT
Keywords: grid pixel voxel field euler projection
Classifier: Development Status :: 4 - Beta
Classifier: License :: OSI Approved :: MIT License
Classifier: Operating System :: OS Independent
Classifier: Intended Audience :: Science/Research
Classifier: Topic :: Scientific/Engineering
Classifier: Topic :: Scientific/Engineering :: Physics
Classifier: Topic :: Scientific/Engineering :: Visualization
Classifier: Programming Language :: Python :: 3
Classifier: Programming Language :: Cython
Classifier: Programming Language :: C
Requires-Python: >=3.6
License-File: LICENSE
Requires-Dist: numpy (>=1.17.3)
Requires-Dist: Cython (>=0.29.13)
Requires-Dist: tqdm (>=4.41.1)
Provides-Extra: docs
Requires-Dist: plotly (>=4.4.1) ; extra == 'docs'
Requires-Dist: matplotlib (>=3.2.2) ; extra == 'docs'
Requires-Dist: pyvista (>=0.31) ; extra == 'docs'
Requires-Dist: Sphinx (>=4.1) ; extra == 'docs'
Requires-Dist: numpydoc (>=1.1) ; extra == 'docs'
Requires-Dist: ipython (>=5.5.0) ; extra == 'docs'
Requires-Dist: pydata-sphinx-theme (>=0.6.3) ; extra == 'docs'
Requires-Dist: pytest (>=3.6.4) ; extra == 'docs'
